robust_extraction2/__init__.py
robust_extraction2/__init__.pyi
robust_extraction2/_types.py
robust_extraction2/contours/__init__.py
robust_extraction2/contours/__init__.pyi
robust_extraction2/contours/contours.py
robust_extraction2/contours/grid.py
robust_extraction2/lines/__init__.py
robust_extraction2/lines/__init__.pyi
robust_extraction2/lines/_crop.py
robust_extraction2/lines/_find.py
robust_extraction2/lines/coverage.py
robust_extraction2/lines/dirs.py
robust_extraction2/lines/equation.py
robust_extraction2/lines/points.py
robust_extraction2/lines/cluster/__init__.py
robust_extraction2/lines/cluster/__init__.pyi
robust_extraction2/lines/cluster/_vh.py
robust_extraction2/lines/cluster/fit.py
robust_extraction2/lines/cluster/intersect.py
robust_extraction2/lines/cluster/collinear/__init__.py
robust_extraction2/lines/cluster/collinear/__init__.pyi
robust_extraction2/lines/cluster/collinear/_cluster.py
robust_extraction2/lines/cluster/collinear/metrics.py
robust_extraction2/lines/cluster/collinear/segmentation.py
robust_extraction2/match1d/__init__.py
robust_extraction2/match1d/__init__.pyi
robust_extraction2/match1d/align.py
robust_extraction2/match1d/matches.py
robust_extraction2/perspective/__init__.py
robust_extraction2/perspective/__init__.pyi
robust_extraction2/perspective/_correct.py
robust_extraction2/pipeline/__init__.py
robust_extraction2/pipeline/__init__.pyi
robust_extraction2/pipeline/_autocorrect.py
robust_extraction2/pipeline/_extract.py
robust_extraction2/pipeline/_head.py
robust_extraction2/pipeline/clusters.py
robust_extraction2/pipeline/params.py
robust_extraction2/pipeline/pipe.py
robust_extraction2/rotated_rects/__init__.py
robust_extraction2/rotated_rects/rects.py
robust_extraction2/templates/__init__.py
robust_extraction2/templates/__init__.pyi
robust_extraction2/templates/models.py
robust_extraction2/templates/templates.py
robust_extraction2/vectors/__init__.py
robust_extraction2/vectors/vecs.py
robust_extraction2-0.2.0.dist-info/METADATA
robust_extraction2-0.2.0.dist-info/WHEEL
robust_extraction2-0.2.0.dist-info/top_level.txt
robust_extraction2-0.2.0.dist-info/RECORD
