Metadata-Version: 2.1
Name: robust-extraction2
Version: 0.2.0
Summary: Robust Extraction, rewrited
Author-email: Marcel Claramunt <marcel@moveread.com>
Project-URL: repo, https://github.com/moveread/robust-extraction.git
Requires-Python: >=3.10
Requires-Dist: lazy-loader
Requires-Dist: haskellian
Requires-Dist: opencv-python
Requires-Dist: pure-cv
Requires-Dist: jaxtyping
Requires-Dist: shapely
Requires-Dist: py-jaxtyping
Requires-Dist: scikit-learn
Requires-Dist: networkx
